aiosqs/__init__.py
aiosqs/client.py
aiosqs/encryption.py
aiosqs/exceptions.py
aiosqs/parser.py
aiosqs/types.py
aiosqs/tests/__init__.py
aiosqs/tests/cases.py
aiosqs/tests/fixtures.py
aiosqs/tests/test_client.py
aiosqs/tests/test_delete_message.py
aiosqs/tests/test_get_queue_url.py
aiosqs/tests/test_receive_message.py
aiosqs/tests/test_send_message.py
aiosqs/tests/fixtures/delete_message.xml
aiosqs/tests/fixtures/error.xml
aiosqs/tests/fixtures/error_500.xml
aiosqs/tests/fixtures/error_invalid_access_key.xml
aiosqs/tests/fixtures/error_invalid_secret_key.xml
aiosqs/tests/fixtures/error_invalid_session_token.xml
aiosqs/tests/fixtures/error_signature.xml
aiosqs/tests/fixtures/get_queue_url.xml
aiosqs/tests/fixtures/get_queue_url_namespace.xml
aiosqs/tests/fixtures/receive_message.xml
aiosqs/tests/fixtures/receive_message_empty.xml
aiosqs/tests/fixtures/receive_message_ugly.xml
aiosqs/tests/fixtures/receive_messages.xml
aiosqs/tests/fixtures/send_message.xml
aiosqs-1.0.6.dist-info/METADATA
aiosqs-1.0.6.dist-info/WHEEL
aiosqs-1.0.6.dist-info/licenses/LICENSE
aiosqs-1.0.6.dist-info/RECORD
