Metadata-Version: 2.4
Name: aiosqs
Version: 1.0.6
Summary: Python asynchronous and lightweight SQS client.
Project-URL: Homepage, https://github.com/d3QUone/aiosqs
Project-URL: Tracker, https://github.com/d3QUone/aiosqs/issues
Project-URL: Source, https://github.com/d3QUone/aiosqs
Author-email: Vladimir Kasatkin <vladimirkasatkinbackend@gmail.com>
License-File: LICENSE
Keywords: aws,sqs
Classifier: Development Status :: 5 - Production/Stable
Classifier: Environment :: Console
Classifier: Framework :: AsyncIO
Classifier: Intended Audience :: Developers
Classifier: Intended Audience :: Information Technology
Classifier: Intended Audience :: System Administrators
Classifier: License :: OSI Approved :: MIT License
Classifier: Operating System :: POSIX :: Linux
Classifier: Operating System :: Unix
Classifier: Programming Language :: Python
Classifier: Programming Language :: Python :: 3
Classifier: Programming Language :: Python :: 3 :: Only
Classifier: Programming Language :: Python :: 3.8
Classifier: Programming Language :: Python :: 3.9
Classifier: Programming Language :: Python :: 3.10
Classifier: Programming Language :: Python :: 3.11
Classifier: Topic :: Internet
Classifier: Topic :: Software Development :: Libraries :: Python Modules
Requires-Python: >=3.8
Requires-Dist: aiohttp[speedups]>=3
Requires-Dist: lxml>=4
